setup.py
az_probability/Binomialdistribution.py
az_probability/Gaussiandistribution.py
az_probability/Generaldistribution.py
az_probability/__init__.py
az_probability.egg-info/PKG-INFO
az_probability.egg-info/SOURCES.txt
az_probability.egg-info/dependency_links.txt
az_probability.egg-info/not-zip-safe
az_probability.egg-info/top_level.txt