Metadata-Version: 2.1
Name: az-probability
Version: 1.0
Summary: Gaussian and Binomial distributions
Home-page: UNKNOWN
Author: Anna Zybina
License: UNKNOWN
Platform: UNKNOWN
